{
  "title": "Article With Media",
  "default": true,
  "group": "Article",
  "model": {
    "mediatype": "image",
    "imagesrc": "/content/assets/themeclean/images/yosemite.jpg",
    "videosrc": "https://www.youtube-nocookie.com/embed/NM2wtte1JRE",
    "mediawidth": "45",
    "toppadding": "10",
    "bottompadding": "10",
    "text": "Dolorem aut qui eligendi atque corporis. Necessitatibus deleniti rerum vel modi consequatur necessitatibus. Accusamus voluptas dolorum debitis doloribus. Esse ea qui dolor quae. Est numquam maiores rem odit. Suscipit ut voluptatum sed et harum."
  }
}